<?xml version="1.0" ?>
<annotation>
    <filename>172_gaussian.jpg</filename>
    <size>
        <width>874</width>
        <height>1280</height>
        <depth>3</depth>
    </size>
    <object>
        <name>Siemens</name>
        <bndbox>
            <xmin>417</xmin>
            <xmax>470</xmax>
            <ymin>168</ymin>
            <ymax>328</ymax>
        </bndbox>
        <difficult>0</difficult>
    </object>
    <object>
        <name>Siemens</name>
        <bndbox>
            <xmin>4</xmin>
            <xmax>68</xmax>
            <ymin>792</ymin>
            <ymax>964</ymax>
        </bndbox>
        <difficult>0</difficult>
    </object>
    <object>
        <name>Siemens</name>
        <bndbox>
            <xmin>147</xmin>
            <xmax>212</xmax>
            <ymin>247</ymin>
            <ymax>424</ymax>
        </bndbox>
        <difficult>0</difficult>
    </object>
    <object>
        <name>AllenBradley</name>
        <bndbox>
            <xmin>495</xmin>
            <xmax>581</xmax>
            <ymin>907</ymin>
            <ymax>1075</ymax>
        </bndbox>
        <difficult>0</difficult>
    </object>
    <object>
        <name>Siemens</name>
        <bndbox>
            <xmin>280</xmin>
            <xmax>375</xmax>
            <ymin>235</ymin>
            <ymax>408</ymax>
        </bndbox>
        <difficult>0</difficult>
    </object>
    <object>
        <name>AllenBradley</name>
        <bndbox>
            <xmin>367</xmin>
            <xmax>492</xmax>
            <ymin>484</ymin>
            <ymax>643</ymax>
        </bndbox>
        <difficult>0</difficult>
    </object>
</annotation>
