<?xml version="1.0" ?>
<annotation>
    <filename>280_gaussian.jpg</filename>
    <size>
        <width>1268</width>
        <height>1280</height>
        <depth>3</depth>
    </size>
    <object>
        <name>Siemens</name>
        <bndbox>
            <xmin>299</xmin>
            <xmax>350</xmax>
            <ymin>1013</ymin>
            <ymax>1160</ymax>
        </bndbox>
        <difficult>0</difficult>
    </object>
    <object>
        <name>Siemens</name>
        <bndbox>
            <xmin>1119</xmin>
            <xmax>1169</xmax>
            <ymin>484</ymin>
            <ymax>627</ymax>
        </bndbox>
        <difficult>0</difficult>
    </object>
    <object>
        <name>AllenBradley</name>
        <bndbox>
            <xmin>649</xmin>
            <xmax>740</xmax>
            <ymin>839</ymin>
            <ymax>972</ymax>
        </bndbox>
        <difficult>0</difficult>
    </object>
    <object>
        <name>AllenBradley</name>
        <bndbox>
            <xmin>1027</xmin>
            <xmax>1120</xmax>
            <ymin>1142</ymin>
            <ymax>1269</ymax>
        </bndbox>
        <difficult>0</difficult>
    </object>
    <object>
        <name>Siemens</name>
        <bndbox>
            <xmin>536</xmin>
            <xmax>582</xmax>
            <ymin>1057</ymin>
            <ymax>1183</ymax>
        </bndbox>
        <difficult>0</difficult>
    </object>
    <object>
        <name>Siemens</name>
        <bndbox>
            <xmin>838</xmin>
            <xmax>882</xmax>
            <ymin>29</ymin>
            <ymax>155</ymax>
        </bndbox>
        <difficult>0</difficult>
    </object>
</annotation>
