<?xml version="1.0" ?>
<annotation>
    <filename>291_gaussian.jpg</filename>
    <size>
        <width>1280</width>
        <height>1085</height>
        <depth>3</depth>
    </size>
    <object>
        <name>Siemens</name>
        <bndbox>
            <xmin>7</xmin>
            <xmax>56</xmax>
            <ymin>295</ymin>
            <ymax>454</ymax>
        </bndbox>
        <difficult>0</difficult>
    </object>
    <object>
        <name>AllenBradley</name>
        <bndbox>
            <xmin>1091</xmin>
            <xmax>1201</xmax>
            <ymin>859</ymin>
            <ymax>1011</ymax>
        </bndbox>
        <difficult>0</difficult>
    </object>
    <object>
        <name>AllenBradley</name>
        <bndbox>
            <xmin>186</xmin>
            <xmax>306</xmax>
            <ymin>479</ymin>
            <ymax>618</ymax>
        </bndbox>
        <difficult>0</difficult>
    </object>
    <object>
        <name>AllenBradley</name>
        <bndbox>
            <xmin>291</xmin>
            <xmax>380</xmax>
            <ymin>856</ymin>
            <ymax>994</ymax>
        </bndbox>
        <difficult>0</difficult>
    </object>
    <object>
        <name>Siemens</name>
        <bndbox>
            <xmin>757</xmin>
            <xmax>806</xmax>
            <ymin>664</ymin>
            <ymax>809</ymax>
        </bndbox>
        <difficult>0</difficult>
    </object>
    <object>
        <name>AllenBradley</name>
        <bndbox>
            <xmin>652</xmin>
            <xmax>764</xmax>
            <ymin>843</ymin>
            <ymax>1003</ymax>
        </bndbox>
        <difficult>0</difficult>
    </object>
    <object>
        <name>Siemens</name>
        <bndbox>
            <xmin>907</xmin>
            <xmax>965</xmax>
            <ymin>71</ymin>
            <ymax>235</ymax>
        </bndbox>
        <difficult>0</difficult>
    </object>
    <object>
        <name>AllenBradley</name>
        <bndbox>
            <xmin>96</xmin>
            <xmax>201</xmax>
            <ymin>879</ymin>
            <ymax>1026</ymax>
        </bndbox>
        <difficult>0</difficult>
    </object>
    <object>
        <name>Siemens</name>
        <bndbox>
            <xmin>418</xmin>
            <xmax>473</xmax>
            <ymin>711</ymin>
            <ymax>864</ymax>
        </bndbox>
        <difficult>0</difficult>
    </object>
</annotation>
