<?xml version="1.0" ?>
<annotation>
    <filename>34_gaussian.jpg</filename>
    <size>
        <width>1194</width>
        <height>1280</height>
        <depth>3</depth>
    </size>
    <object>
        <name>Siemens</name>
        <bndbox>
            <xmin>1125</xmin>
            <xmax>1171</xmax>
            <ymin>686</ymin>
            <ymax>837</ymax>
        </bndbox>
        <difficult>0</difficult>
    </object>
    <object>
        <name>Siemens</name>
        <bndbox>
            <xmin>58</xmin>
            <xmax>100</xmax>
            <ymin>765</ymin>
            <ymax>903</ymax>
        </bndbox>
        <difficult>0</difficult>
    </object>
    <object>
        <name>Siemens</name>
        <bndbox>
            <xmin>761</xmin>
            <xmax>830</xmax>
            <ymin>827</ymin>
            <ymax>973</ymax>
        </bndbox>
        <difficult>0</difficult>
    </object>
    <object>
        <name>AllenBradley</name>
        <bndbox>
            <xmin>197</xmin>
            <xmax>290</xmax>
            <ymin>569</ymin>
            <ymax>704</ymax>
        </bndbox>
        <difficult>0</difficult>
    </object>
    <object>
        <name>AllenBradley</name>
        <bndbox>
            <xmin>729</xmin>
            <xmax>817</xmax>
            <ymin>382</ymin>
            <ymax>517</ymax>
        </bndbox>
        <difficult>0</difficult>
    </object>
    <object>
        <name>Siemens</name>
        <bndbox>
            <xmin>1130</xmin>
            <xmax>1177</xmax>
            <ymin>39</ymin>
            <ymax>180</ymax>
        </bndbox>
        <difficult>0</difficult>
    </object>
    <object>
        <name>AllenBradley</name>
        <bndbox>
            <xmin>163</xmin>
            <xmax>286</xmax>
            <ymin>709</ymin>
            <ymax>848</ymax>
        </bndbox>
        <difficult>0</difficult>
    </object>
    <object>
        <name>AllenBradley</name>
        <bndbox>
            <xmin>474</xmin>
            <xmax>589</xmax>
            <ymin>179</ymin>
            <ymax>337</ymax>
        </bndbox>
        <difficult>0</difficult>
    </object>
    <object>
        <name>AllenBradley</name>
        <bndbox>
            <xmin>516</xmin>
            <xmax>614</xmax>
            <ymin>1021</ymin>
            <ymax>1159</ymax>
        </bndbox>
        <difficult>0</difficult>
    </object>
</annotation>
